gitrisk
