Metadata-Version: 1.0
Name: gitrisk
Version: 0.1.0
Summary: A tool for determining which tickets included in a merge might be at risk of regressions
Home-page: http://github.com/jwir3/git-risk
Author: Scott Johnson
Author-email: jaywir3@gmail.com
License: Mozilla Public License v2.0
Platform: UNKNOWN
